{
  "title": "Is It Web Or Photoshop?",
  "excerpt": "Experiment with creating print-like, magazine-like, tv-like websites",
  "thumb": "yale_mobile.png",
  "template": "article",
  "categories": [
    "design"
  ],
  "url": "is-it-web-or-photoshop",
  "date": "2015-12-25",
  "display": [
    "title",
    "title_with_url",
    "categories",
    "date",
    "slides",
    "more"
  ],
  "slides": [
    {
      "title": "Mars Maiers",
      "name": "marsmaiers",
      "extension": ".jpg"
    },
    {
      "title": "Yale / Paul Rand",
      "name": "yale"
    },
    {
      "title": "Bloomberg",
      "name": "bloomberg",
      "link": {
        "title": "Bloomberg Business Week",
        "url": "http://www.bloomberg.com/businessweek/design-conference/",
        "type": "external"
      }
    },
    {
      "title": "Architetti Arco Alpino",
      "name": "arco",
      "link": {
        "title": "Architetti Arco Alpino",
        "url": "http://www.architettiarcoalpino.it/",
        "type": "external"
      }
    },
    {
      "title": "Holz.re",
      "name": "holz"
    },
    {
      "title": "After All Studio",
      "name": "afterall",
      "link": {
        "title": "After All Studio",
        "url": "http://afterallstudio.com/",
        "type": "external"
      }
    }
  ]
}
